odoo/addons/website_slides_attendees_completed_time/README.rst
odoo/addons/website_slides_attendees_completed_time/__init__.py
odoo/addons/website_slides_attendees_completed_time/__manifest__.py
odoo/addons/website_slides_attendees_completed_time/post_install.py
odoo/addons/website_slides_attendees_completed_time/i18n/website_slides_attendees_completed_time.pot
odoo/addons/website_slides_attendees_completed_time/models/__init__.py
odoo/addons/website_slides_attendees_completed_time/models/slide_channel_partner.py
odoo/addons/website_slides_attendees_completed_time/readme/CONTRIBUTORS.md
odoo/addons/website_slides_attendees_completed_time/readme/DESCRIPTION.md
odoo/addons/website_slides_attendees_completed_time/readme/USAGE.md
odoo/addons/website_slides_attendees_completed_time/static/description/attendees_tree_view.png
odoo/addons/website_slides_attendees_completed_time/static/description/icon.png
odoo/addons/website_slides_attendees_completed_time/static/description/index.html
odoo/addons/website_slides_attendees_completed_time/tests/__init__.py
odoo/addons/website_slides_attendees_completed_time/tests/test_attendees_completed_time.py
odoo/addons/website_slides_attendees_completed_time/views/slide_channel_partner_views.xml
odoo_addon_website_slides_attendees_completed_time-16.0.1.0.0.2.dist-info/METADATA
odoo_addon_website_slides_attendees_completed_time-16.0.1.0.0.2.dist-info/WHEEL
odoo_addon_website_slides_attendees_completed_time-16.0.1.0.0.2.dist-info/top_level.txt
odoo_addon_website_slides_attendees_completed_time-16.0.1.0.0.2.dist-info/RECORD
